Metadata-Version: 2.1
Name: multi-folder-pkg-deps-insomniapx
Version: 0.0.1
Summary: A multi-folder package (with dependency) for insomniapx
Home-page: https://github.com/insomniapx-python-projects/py_package.git
Author: insomniapx
Author-email: insomniapx@gmail.com
License: UNKNOWN
Platform: UNKNOWN
Requires-Python: >=3.6
License-File: LICENSE
Requires-Dist: pytest
Requires-Dist: numpy (>=1.0.4)
